{
  "users": {
    "warwick": {
      "password": "gargameel",
      "friends": [
        "viego",
        "elise"
      ]
    },
    "nautilus": {
      "password": "wateereman123",
      "friends": []
    },
    "regen": {
      "password": "123",
      "friends": []
    },
    "dawd": {
      "password": "adasd",
      "friends": []
    },
    "philip": {
      "password": "123",
      "friends": [
        "regen",
        "regen",
        "",
        "hej",
        "warwick"
      ]
    },
    "testing": {
      "password": "test",
      "friends": []
    }
  }
}